sgp/__init__.py
sgp/ast_node_types.py
sgp/main.py
sgp/sgp_error_listener.py
sgp/sgp_parser.py
sgp/sgp_visitor.py
sgp/tokens.py
sgp/utils.py
sgp/parser/SolidityLexer.py
sgp/parser/SolidityListener.py
sgp/parser/SolidityParser.py
sgp/parser/SolidityVisitor.py
sgp/parser/__init__.py
openzeppelin_solidity_grammar_parser-0.0.5.dist-info/LICENSE
openzeppelin_solidity_grammar_parser-0.0.5.dist-info/METADATA
openzeppelin_solidity_grammar_parser-0.0.5.dist-info/WHEEL
openzeppelin_solidity_grammar_parser-0.0.5.dist-info/top_level.txt
openzeppelin_solidity_grammar_parser-0.0.5.dist-info/RECORD
